[
	{
		"city": "香港"
	},
	{
		"city": "澳门"
	},
	{
		"city": "潮州"
	},
	{
		"city": "东莞"
	},
	{
		"city": "佛山"
	},
	{
		"city": "广州"
	},
	{
		"city": "河源"
	},
	{
		"city": "惠州"
	},
	{
		"city": "江门"
	},
	{
		"city": "揭阳"
	},
	{
		"city": "茂名"
	},
	{
		"city": "梅州"
	},
	{
		"city": "清远"
	},
	{
		"city": "汕头"
	},
	{
		"city": "汕尾"
	},
	{
		"city": "韶关"
	},
	{
		"city": "深圳"
	},
	{
		"city": "阳江"
	},
	{
		"city": "云浮"
	},
	{
		"city": "湛江"
	},
	{
		"city": "肇庆"
	},
	{
		"city": "中山"
	},
	{
		"city": "珠海"
	},
	{
		"city": "百色"
	},
	{
		"city": "北海"
	},
	{
		"city": "崇左"
	},
	{
		"city": "防城港"
	},
	{
		"city": "贵港"
	},
	{
		"city": "桂林"
	},
	{
		"city": "河池"
	},
	{
		"city": "贺州"
	},
	{
		"city": "来宾"
	},
	{
		"city": "柳州"
	},
	{
		"city": "南宁"
	},
	{
		"city": "钦州"
	},
	{
		"city": "梧州"
	},
	{
		"city": "玉林"
	},
	{
		"city": "常德"
	},
	{
		"city": "长沙"
	},
	{
		"city": "郴州"
	},
	{
		"city": "衡阳"
	},
	{
		"city": "怀化"
	},
	{
		"city": "娄底"
	},
	{
		"city": "邵阳"
	},
	{
		"city": "湘潭"
	},
	{
		"city": "湘西"
	},
	{
		"city": "益阳"
	},
	{
		"city": "永州"
	},
	{
		"city": "岳阳"
	},
	{
		"city": "张家界"
	},
	{
		"city": "株洲"
	},
	{
		"city": "抚州"
	},
	{
		"city": "赣州"
	},
	{
		"city": "吉安"
	},
	{
		"city": "景德镇"
	},
	{
		"city": "九江"
	},
	{
		"city": "南昌"
	},
	{
		"city": "萍乡"
	},
	{
		"city": "上饶"
	},
	{
		"city": "新余"
	},
	{
		"city": "宜春"
	},
	{
		"city": "鹰潭"
	},
	{
		"city": "福州"
	},
	{
		"city": "龙岩"
	},
	{
		"city": "南平"
	},
	{
		"city": "宁德"
	},
	{
		"city": "莆田"
	},
	{
		"city": "泉州"
	},
	{
		"city": "三明"
	},
	{
		"city": "厦门"
	},
	{
		"city": "漳州"
	},
	{
		"city": "白沙"
	},
	{
		"city": "保亭"
	},
	{
		"city": "昌江"
	},
	{
		"city": "澄迈"
	},
	{
		"city": "儋州"
	},
	{
		"city": "定安"
	},
	{
		"city": "东方"
	},
	{
		"city": "海口"
	},
	{
		"city": "乐东"
	},
	{
		"city": "临高"
	},
	{
		"city": "陵水"
	},
	{
		"city": "琼海"
	},
	{
		"city": "琼中"
	},
	{
		"city": "三亚"
	},
	{
		"city": "屯昌"
	},
	{
		"city": "万宁"
	},
	{
		"city": "文昌"
	},
	{
		"city": "五指山"
	},
	{
		"city": "安顺"
	},
	{
		"city": "毕节"
	},
	{
		"city": "贵阳"
	},
	{
		"city": "六盘水"
	},
	{
		"city": "黔东南"
	},
	{
		"city": "黔南"
	},
	{
		"city": "黔西南"
	},
	{
		"city": "铜仁"
	},
	{
		"city": "遵义"
	},
	{
		"city": "保山"
	},
	{
		"city": "楚雄"
	},
	{
		"city": "大理"
	},
	{
		"city": "德宏"
	},
	{
		"city": "迪庆"
	},
	{
		"city": "红河"
	},
	{
		"city": "昆明"
	},
	{
		"city": "丽江"
	},
	{
		"city": "临沧"
	},
	{
		"city": "怒江"
	},
	{
		"city": "普洱"
	},
	{
		"city": "曲靖"
	},
	{
		"city": "文山"
	},
	{
		"city": "西双版纳"
	},
	{
		"city": "玉溪"
	},
	{
		"city": "昭通"
	},
	{
		"city": "重庆"
	},
	{
		"city": "阿坝"
	},
	{
		"city": "巴中"
	},
	{
		"city": "成都"
	},
	{
		"city": "达州"
	},
	{
		"city": "德阳"
	},
	{
		"city": "甘孜"
	},
	{
		"city": "广安"
	},
	{
		"city": "广元"
	},
	{
		"city": "乐山"
	},
	{
		"city": "凉山"
	},
	{
		"city": "泸州"
	},
	{
		"city": "眉山"
	},
	{
		"city": "绵阳"
	},
	{
		"city": "南充"
	},
	{
		"city": "内江"
	},
	{
		"city": "攀枝花"
	},
	{
		"city": "遂宁"
	},
	{
		"city": "雅安"
	},
	{
		"city": "宜宾"
	},
	{
		"city": "资阳"
	},
	{
		"city": "自贡"
	},
	{
		"city": "鄂州"
	},
	{
		"city": "恩施"
	},
	{
		"city": "黄冈"
	},
	{
		"city": "黄石"
	},
	{
		"city": "荆门"
	},
	{
		"city": "荆州"
	},
	{
		"city": "潜江"
	},
	{
		"city": "神农架"
	},
	{
		"city": "十堰"
	},
	{
		"city": "随州"
	},
	{
		"city": "天门"
	},
	{
		"city": "武汉"
	},
	{
		"city": "仙桃"
	},
	{
		"city": "咸宁"
	},
	{
		"city": "襄阳"
	},
	{
		"city": "孝感"
	},
	{
		"city": "宜昌"
	},
	{
		"city": "安庆"
	},
	{
		"city": "蚌埠"
	},
	{
		"city": "亳州"
	},
	{
		"city": "池州"
	},
	{
		"city": "滁州"
	},
	{
		"city": "阜阳"
	},
	{
		"city": "合肥"
	},
	{
		"city": "淮北"
	},
	{
		"city": "淮南"
	},
	{
		"city": "黄山"
	},
	{
		"city": "六安"
	},
	{
		"city": "马鞍山"
	},
	{
		"city": "宿州"
	},
	{
		"city": "铜陵"
	},
	{
		"city": "芜湖"
	},
	{
		"city": "宣城"
	},
	{
		"city": "杭州"
	},
	{
		"city": "湖州"
	},
	{
		"city": "嘉兴"
	},
	{
		"city": "金华"
	},
	{
		"city": "丽水"
	},
	{
		"city": "宁波"
	},
	{
		"city": "衢州"
	},
	{
		"city": "绍兴"
	},
	{
		"city": "台州"
	},
	{
		"city": "温州"
	},
	{
		"city": "舟山"
	},
	{
		"city": "上海"
	},
	{
		"city": "常州"
	},
	{
		"city": "淮安"
	},
	{
		"city": "连云港"
	},
	{
		"city": "南京"
	},
	{
		"city": "南通"
	},
	{
		"city": "苏州"
	},
	{
		"city": "宿迁"
	},
	{
		"city": "泰州"
	},
	{
		"city": "无锡"
	},
	{
		"city": "徐州"
	},
	{
		"city": "盐城"
	},
	{
		"city": "扬州"
	},
	{
		"city": "镇江"
	},
	{
		"city": "信阳"
	},
	{
		"city": "驻马店"
	},
	{
		"city": "南阳"
	},
	{
		"city": "周口"
	},
	{
		"city": "漯河"
	},
	{
		"city": "许昌"
	},
	{
		"city": "平顶山"
	},
	{
		"city": "洛阳"
	},
	{
		"city": "三门峡"
	},
	{
		"city": "商丘"
	},
	{
		"city": "开封"
	},
	{
		"city": "郑州"
	},
	{
		"city": "安康"
	},
	{
		"city": "汉中"
	},
	{
		"city": "商洛"
	},
	{
		"city": "西安"
	},
	{
		"city": "宝鸡"
	},
	{
		"city": "陇南"
	},
	{
		"city": "天水"
	}
]